[{"link": ["/"]},
{"link": ["/Computers/"]},
{"link": ["/Computers/Programming/"]},
{"link": ["/Computers/Programming/Languages/"]},
{"link": ["/Computers/Programming/Languages/Python/"]},
{"link": []},
{"link": ["/Computers/Programming/Languages/Python/Resources/"]},
{"link": ["http://www.baypiggies.net/"]},
{"link": ["http://www.chipy.org/"]},
{"link": ["http://groups.google.com/group/clepy/"]},
{"link": ["http://www.dfwpython.org/"]},
{"link": ["http://www.zope.org/Members/poster/zpug_info"]},
{"link": ["https://wiki.python.org/moin/FrontRangePythoneers"]},
{"link": ["http://tech.groups.yahoo.com/group/grimpypers/"]},
{"link": ["http://groups.google.com/group/michipug"]},
{"link": ["http://www.omahapython.org/"]},
{"link": ["http://opag.ca/"]},
{"link": ["http://www.meetup.com/python-atlanta/"]},
{"link": ["http://www.engcorp.com/pygta"]},
{"link": ["http://www.seapig.org/"]},
{"link": ["http://trizpug.org/"]},
{"link": ["http://groups.google.com/group/utahpython"]},
{"link": ["/"]},
{"link": ["/Computers/"]},
{"link": ["/Computers/Programming/"]},
{"link": ["/Computers/Programming/Languages/"]},
{"link": ["/Computers/Programming/Languages/Python/"]},
{"link": []},
{"link": ["/Computers/Programming/Personal_Pages/"]},
{"link": ["http://radio-weblogs.com/0102677/categories/python/"]},
{"link": ["http://randombytes.blogspot.com/"]},
{"link": ["http://www.blendedtechnologies.com/"]},
{"link": ["http://rgruet.free.fr/"]},
{"link": ["http://starship.python.net/crew/hinsen/"]},
{"link": ["http://www.amk.ca/"]},
{"link": ["http://www.learningpython.com/"]},
{"link": ["http://effbot.org/"]},
{"link": ["http://www.codeape.org/"]},
{"link": ["https://www.python.org/~guido/"]},
{"link": ["/"]},
{"link": ["/Computers/"]},
{"link": ["/Computers/Programming/"]},
{"link": ["/Computers/Programming/Languages/"]},
{"link": ["/Computers/Programming/Languages/Python/"]},
{"link": []},
{"link": ["/Computers/Programming/Languages/Python/Modules/Web/"]},
{"link": ["/Computers/Programming/Languages/Python/Web/Templating_Libraries/"]},
{"link": ["/Computers/Programming/Languages/Python/Web/Web_Frameworks/"]},
{"link": ["/"]},
{"link": ["/Computers/"]},
{"link": ["/Computers/Programming/"]},
{"link": ["/Computers/Programming/Languages/"]},
{"link": ["/Computers/Programming/Languages/Python/"]},
{"link": []},
{"link": ["/Computers/Software/Internet/Servers/Application/Zope/"]},
{"link": ["/Computers/Companies/Software_Development/"]},
{"link": ["http://www.crazy-compilers.com/bridgekeeper/"]},
{"link": ["http://www.crazy-compilers.com/decompyle/"]},
{"link": ["http://www.pythonware.com/"]},
{"link": ["http://www.reportlab.com/"]},
{"link": ["http://www.xellsoft.com/"]},
{"link": ["/"]},
{"link": ["/Computers/"]},
{"link": ["/Computers/Programming/"]},
{"link": ["/Computers/Programming/Languages/"]},
{"link": ["/Computers/Programming/Languages/Python/"]},
{"link": []},
{"link": ["/Computers/Programming/FAQs%2C_Help%2C_and_Tutorials/"]},
{"link": ["/Computers/Programming/Languages/Python/Articles_and_Reviews/"]},
{"link": ["/World/Deutsch/Computer/Programmieren/Sprachen/Python/Anleitungen%2C_Hilfen_und_FAQs"]},
{"link": ["https://www.python.org/doc/"]},
{"link": ["http://python.about.com/"]},
{"link": ["http://www.sthurlow.com/python/"]},
{"link": ["http://phaseit.net/claird/comp.lang.python/web_python.html"]},
{"link": ["http://python.net/~goodger/projects/pycon/2007/idiomatic/handout.html"]},
{"link": ["http://www.upriss.org.uk/python/PythonCourse.html"]},
{"link": ["http://www.djangobook.com/"]},
{"link": ["http://www.ddj.com/184412536"]},
{"link": ["http://hetland.org/writing/instant-hacking.html"]},
{"link": ["http://hetland.org/writing/instant-python.html"]},
{"link": ["https://hkn.eecs.berkeley.edu/~dyoo/python/idle_intro/"]},
{"link": ["http://www.objectsbydesign.com/projects/python_uml.html"]},
{"link": ["http://www.cs.virginia.edu/~lab2q/"]},
{"link": ["https://wiki.python.org/moin/DatabaseProgramming/"]},
{"link": ["https://wiki.python.org/moin/BeginnersGuide"]},
{"link": ["http://www.linuxjournal.com/article/3946"]},
{"link": ["http://www.dickbaldwin.com/tocpyth.htm"]},
{"link": ["http://www.brunningonline.net/simon/python/PQR.html"]},
{"link": ["http://code.activestate.com/recipes/langs/python/"]},
{"link": ["https://www.python.org/community/sigs/"]},
{"link": ["http://www.mtdev.com/2002/08/python-tutorial"]},
{"link": ["http://stsdas.stsci.edu/pyraf/python_quick_tour.html"]},
{"link": ["http://infohost.nmt.edu/tcc/help/pubs/lang.html"]},
{"link": ["http://www.tutorialized.com/tutorials/Python/1"]},
{"link": ["http://en.wikibooks.org/wiki/Programming:Python"]},
{"link": ["http://www.devshed.com/c/a/Python/Writing-CGI-Programs-in-Python/"]},
{"link": ["/"]},
{"link": ["/Computers/"]},
{"link": ["/Computers/Programming/"]},
{"link": ["/Computers/Programming/Languages/"]},
{"link": ["/Computers/Programming/Languages/Python/"]},
{"link": []},
{"link": ["/Computers/Computer_Science/Conferences/"]},
{"link": ["/Computers/Programming/Conferences/"]},
{"link": ["/Computers/Programming/Languages/Perl/Conferences/"]},
{"link": ["/Computers/Programming/Languages/Ruby/Conferences/"]},
{"link": ["/"]},
{"link": ["/Computers/"]},
{"link": ["/Computers/Programming/"]},
{"link": ["/Computers/Programming/Languages/"]},
{"link": ["/Computers/Programming/Languages/Python/"]},
{"link": []},
{"link": ["/Computers/Programming/Resources/"]},
{"link": ["http://www.pythonware.com/daily/"]},
{"link": ["http://oreilly.com/python/"]},
{"link": ["https://www.python.org/dev/"]},
{"link": ["http://win32com.goermezer.de/"]},
{"link": ["/"]},
{"link": ["/Computers/"]},
{"link": ["/Computers/Programming/"]},
{"link": ["/Computers/Programming/Languages/"]},
{"link": ["/Computers/Programming/Languages/Python/"]},
{"link": []},
{"link": ["/Computers/Programming/Languages/Python/Resources/"]},
{"link": ["/"]},
{"link": ["/Computers/"]},
{"link": ["/Computers/Programming/"]},
{"link": ["/Computers/Programming/Languages/"]},
{"link": ["/Computers/Programming/Languages/Python/"]},
{"link": []},
{"link": ["/Computers/Programming/Languages/Python/Resources/"]},
{"link": ["/Computers/Programming/Languages/Ruby/Books/"]},
{"link": ["/World/Deutsch/Computer/Programmieren/Sprachen/Python/B%C3%BCcher"]},
{"link": ["/World/Russian/%D0%9A%D0%BE%D0%BC%D0%BF%D1%8C%D1%8E%D1%82%D0%B5%D1%80%D1%8B/%D0%9F%D1%80%D0%BE%D0%B3%D1%80%D0%B0%D0%BC%D0%BC%D0%B8%D1%80%D0%BE%D0%B2%D0%B0%D0%BD%D0%B8%D0%B5/%D0%AF%D0%B7%D1%8B%D0%BA%D0%B8/Python/%D0%9A%D0%BD%D0%B8%D0%B3%D0%B8"]},
{"link": ["http://www.pearsonhighered.com/educator/academic/product/0,,0130260363,00%2Ben-USS_01DBC.html"]},
{"link": ["http://www.brpreiss.com/books/opus7/html/book.html"]},
{"link": ["http://www.diveintopython.net/"]},
{"link": ["http://rhodesmill.org/brandon/2011/foundations-of-python-network-programming/"]},
{"link": ["http://www.techbooksforfree.com/perlpython.shtml"]},
{"link": ["http://www.freetechbooks.com/python-f6.html"]},
{"link": ["http://greenteapress.com/thinkpython/"]},
{"link": ["http://www.network-theory.co.uk/python/intro/"]},
{"link": ["http://www.freenetpages.co.uk/hp/alan.gauld/"]},
{"link": ["http://www.wiley.com/WileyCDA/WileyTitle/productCd-0471219754.html"]},
{"link": ["http://hetland.org/writing/practical-python/"]},
{"link": ["http://sysadminpy.com/"]},
{"link": ["http://www.qtrac.eu/py3book.html"]},
{"link": ["http://www.wiley.com/WileyCDA/WileyTitle/productCd-0764548077.html"]},
{"link": ["https://www.packtpub.com/python-3-object-oriented-programming/book"]},
{"link": ["http://www.network-theory.co.uk/python/language/"]},
{"link": ["http://www.pearsonhighered.com/educator/academic/product/0,,0130409561,00%2Ben-USS_01DBC.html"]},
{"link": ["http://www.informit.com/store/product.aspx?isbn=0201616165&redir=1"]},
{"link": ["http://www.pearsonhighered.com/educator/academic/product/0,,0201748843,00%2Ben-USS_01DBC.html"]},
{"link": ["http://www.informit.com/store/product.aspx?isbn=0672317354"]},
{"link": ["http://gnosis.cx/TPiP/"]},
{"link": ["http://www.informit.com/store/product.aspx?isbn=0130211192"]},
{"link": ["/"]},
{"link": ["/Computers/"]},
{"link": ["/Computers/Programming/"]},
{"link": ["/Computers/Programming/Languages/"]},
{"link": ["/Computers/Programming/Languages/Python/"]},
{"link": []},
{"link": ["/Computers/Programming/Languages/Python/Modules/Directories/"]},
{"link": ["/Computers/Programming/Languages/Python/Modules/Cryptography/"]},
{"link": ["/Computers/Programming/Languages/Python/Modules/Databases_and_Persistence/"]},
{"link": ["/Computers/Programming/Languages/Python/Modules/Distributed_Computing/"]},
{"link": ["/Computers/Programming/Languages/Python/Modules/Graphics/"]},
{"link": ["/Computers/Programming/Languages/Python/Modules/GUI/"]},
{"link": ["/Computers/Programming/Languages/Python/Modules/Math_and_Calculations/"]},
{"link": ["/Computers/Programming/Languages/Python/Modules/Network/"]},
{"link": ["/Computers/Programming/Languages/Python/Modules/Scientific/"]},
{"link": ["/Computers/Programming/Languages/Python/Modules/Text_Processing/"]},
{"link": ["/Computers/Programming/Languages/Python/Modules/Web/"]},
{"link": ["/Computers/Programming/Languages/Python/Modules/XML/"]},
{"link": ["/Computers/Programming/Languages/Python/Modules/Data_Formats/"]},
{"link": ["/Computers/Programming/Languages/Python/Modules/Email/"]},
{"link": ["/Computers/Programming/Languages/Python/Modules/Platform_Specific/"]},
{"link": ["/Computers/Programming/Languages/Python/Modules/Terminal_IO/"]},
{"link": ["/Computers/Programming/Libraries/"]},
{"link": ["http://www.red-dove.com/python_config.html"]},
{"link": ["http://expectpy.sourceforge.net/"]},
{"link": ["https://www.mems-exchange.org/software/"]},
{"link": ["http://www.red-dove.com/python_logging.html"]},
{"link": ["http://www.egenix.com/products/python/mxBase/"]},
{"link": ["http://www.ailab.si/orange"]},
{"link": ["http://www.parallelpython.com/"]},
{"link": ["http://www.livinglogic.de/Python/sisyphus/"]},
{"link": ["http://www.speech.kth.se/snack/"]},
{"link": ["http://txobject.sourceforge.net/"]},
{"link": ["/"]},
{"link": ["/Computers/"]},
{"link": ["/Computers/Programming/"]},
{"link": ["/Computers/Programming/Languages/"]},
{"link": ["/Computers/Programming/Languages/Python/"]},
{"link": []},
{"link": ["/Computers/Programming/Languages/Python/Resources/"]},
{"link": ["http://gnosis.cx/publish/tech_index_cp.html"]},
{"link": ["http://www.linuxfocus.org/English/July2000/article160.shtml"]},
{"link": ["http://oreilly.com/pub/a/oreilly/frank/rossum_1099.html"]},
{"link": ["http://www.rmi.net/~lutz/advocacy.html"]},
{"link": ["http://www.python.org/dev/peps/"]},
{"link": ["http://en.wikipedia.org/wiki/Python_programming_language"]},
{"link": ["http://www.linuxplanet.com/linuxplanet/tutorials/1132/1/"]},
{"link": ["http://www.ibm.com/developerworks/views/webservices/libraryview.jsp?search_by=python+web+services+developer"]},
{"link": ["http://linuxfr.org/2003/03/12/11491.html"]},
{"link": ["http://www.artima.com/intv/guido.html"]},
{"link": ["http://www.xml.com/pub/a/2002/11/13/py-xml.html"]},
{"link": ["http://www.ibm.com/developerworks/linux/library/l-pypers.html"]},
{"link": ["http://www.xml.com/pub/a/2002/10/16/py-xml.html"]},
{"link": ["http://www.ibm.com/developerworks/linux/library/l-psyco.html"]},
{"link": ["http://www.linuxjournal.com/article/5821"]},
{"link": ["http://www.techrepublic.com/article/pick-up-some-python-with-this-script-walk-through/"]},
{"link": ["http://www.techrepublic.com/article/space-shuttle-engineers-use-python-to-streamline-mission-design/"]},
{"link": ["http://www.linux-mag.com/id/1025/"]},
{"link": ["http://www.linuxjournal.com/article/4540"]},
{"link": ["http://www.linuxjournal.com/article/3641"]},
{"link": ["http://www.linuxjournal.com/article/3882"]},
{"link": ["http://www.linuxjournal.com/article/5028"]},
{"link": ["/"]},
{"link": ["/Computers/"]},
{"link": ["/Computers/Programming/"]},
{"link": ["/Computers/Programming/Languages/"]},
{"link": ["/Computers/Programming/Languages/Python/"]},
{"link": []},
{"link": ["https://www.python.org/download/"]},
{"link": ["http://www.codeplex.com/wikipage?ProjectName=IronPython"]},
{"link": ["http://sourceforge.net/projects/jython/"]},
{"link": ["http://pythonnet.sourceforge.net/"]},
{"link": ["http://www.stackless.com/"]},
{"link": ["/"]},
{"link": ["/Computers/"]},
{"link": ["/Computers/Programming/"]},
{"link": ["/Computers/Programming/Languages/"]},
{"link": ["/Computers/Programming/Languages/Python/"]},
{"link": []},
{"link": ["/Computers/Programming/Languages/Python/Development_Tools/Deployment/"]},
{"link": ["/Computers/Programming/Languages/Python/Development_Tools/Documentation_Tools/"]},
{"link": ["/Computers/Programming/Languages/Python/Development_Tools/Foreign_Language_Interfaces/"]},
{"link": ["/Computers/Programming/Languages/Python/Development_Tools/GUI_Builders/"]},
{"link": ["/Computers/Programming/Languages/Python/Development_Tools/Integrated_Development_Environments/"]},
{"link": ["/Computers/Programming/Languages/Python/Development_Tools/Performance_and_Testing/"]},
{"link": ["/Computers/Programming/Development_Tools/"]},
{"link": ["http://hapdebugger.sourceforge.net/"]},
{"link": ["http://ipython.scipy.org/"]},
{"link": ["http://sourceforge.net/projects/pycrust/"]},
{"link": ["http://pymerase.sourceforge.net/"]},
{"link": ["http://www.logilab.org/2560/"]},
{"link": ["http://tix.sourceforge.net/Tixapps/"]},
{"link": ["http://winpdb.org/"]}]